anyforce/__init__.py
anyforce/coro.py
anyforce/py.typed
anyforce/api/__init__.py
anyforce/api/api.py
anyforce/api/exceptions.py
anyforce/api/g.py
anyforce/api/scheduler/__init__.py
anyforce/api/scheduler/rq_worker.py
anyforce/api/scheduler/typing.py
anyforce/api/security/__init__.py
anyforce/api/security/jwt.py
anyforce/api/security/oauth2.py
anyforce/api/security/session.py
anyforce/json/__init__.py
anyforce/logging/__init__.py
anyforce/logging/factory/__init__.py
anyforce/logging/factory/multi.py
anyforce/model/__init__.py
anyforce/model/base.py
anyforce/model/enum.py
anyforce/model/fields.py
anyforce/model/functions.py
anyforce/model/queryset.py
anyforce/model/recoverable.py
anyforce/model/validators.py
anyforce/test/__init__.py
anyforce/test/api.py
anyforce/test/fixtures.py
anyforce/test/request.py
anyforce/typing/__init__.py
anyforce-0.46.1.dist-info/METADATA
anyforce-0.46.1.dist-info/WHEEL
anyforce-0.46.1.dist-info/top_level.txt
anyforce-0.46.1.dist-info/RECORD
