Metadata-Version: 2.4
Name: anyforce
Version: 0.46.1
Author-email: exherb <i@4leaf.me>
Project-URL: homepage, https://github.com/42signal/anyforce
Requires-Python: >=3.11
Requires-Dist: uvicorn[standard]>=0.30.3
Requires-Dist: pydantic[email]>2.0.0
Requires-Dist: python-jose[cryptography]>=3.3.0
Requires-Dist: tortoise-orm>=0.25.0
Requires-Dist: orjson>=3.10.6
Requires-Dist: aiohttp[speedups]>=3.9.5
Requires-Dist: starlette-context>=0.3.6
Requires-Dist: itsdangerous>=2.2.0
Requires-Dist: python-dateutil>=2.9.0.post0
Requires-Dist: rq>=1.16.2
Requires-Dist: uvloop>=0.19.0
Requires-Dist: PyYAML>=6.0.1
Requires-Dist: fastapi>=0.111.1
Requires-Dist: pydantic-settings>=2.3.4
Requires-Dist: structlog>=25.1.0
